klabutils/__init__.py
klabutils/model.py
klabutils-0.1.0.dist-info/DESCRIPTION.rst
klabutils-0.1.0.dist-info/METADATA
klabutils-0.1.0.dist-info/RECORD
klabutils-0.1.0.dist-info/WHEEL
klabutils-0.1.0.dist-info/metadata.json
klabutils-0.1.0.dist-info/top_level.txt
