Metadata-Version: 2.0
Name: klabutils
Version: 0.1.0
Summary: K-Lab utils package
Home-page: https://github.com/Kesci/klabutils
Author: Kesci
Author-email: mike@kesci.com
License: UNKNOWN
Keywords: kesci klab utils
Platform: UNKNOWN
Classifier: Development Status :: 3 - Alpha
Classifier: Intended Audience :: Developers
Classifier: Topic :: Software Development :: Libraries
Classifier: License :: OSI Approved :: MIT License
Classifier: Programming Language :: Python :: 2.7
Classifier: Programming Language :: Python :: 3
Classifier: Programming Language :: Python :: 3.4
Classifier: Programming Language :: Python :: 3.5
Classifier: Programming Language :: Python :: 3.6
Requires-Dist: requests (>=2.11.1)
